np_logging/__init__.py
np_logging/config.py
np_logging/default_logging_config.yaml
np_logging/handlers.py
np_logging/np_logging.py
np_logging/package_config.yaml
np_logging/utils.py
np_logging-0.5.1.dist-info/METADATA
np_logging-0.5.1.dist-info/WHEEL
np_logging-0.5.1.dist-info/RECORD
