Metadata-Version: 2.1
Name: np-logging
Version: 0.5.1
Summary: Pre-configured file, web, and email logging for Mindscope neuropixels projects, repackaging code from AIBS mpeconfig.
Author: Ben Hardcastle
Author-email: ben.hardcastle@alleninstitute.org
Maintainer: Ben Hardcastle
Maintainer-email: ben.hardcastle@alleninstitute.org
Requires-Python: >=3.7,<4.0
Classifier: License :: OSI Approved :: MIT License
Classifier: Operating System :: OS Independent
Classifier: Programming Language :: Python :: 3
Classifier: Programming Language :: Python :: 3.7
Classifier: Programming Language :: Python :: 3.8
Classifier: Programming Language :: Python :: 3.9
Classifier: Programming Language :: Python :: 3.10
Classifier: Programming Language :: Python :: 3.11
Classifier: Programming Language :: Python :: 3
Requires-Dist: importlib_resources (>1.4)
Requires-Dist: np_config (>0.4.12)
Project-URL: Bug Tracker, https://github.com/alleninstitute/np_logging/issues
Project-URL: Repository, https://github.com/alleninstitute/np_logging
